ttxc/__init__.py
ttxc/constants.py
ttxc/main.py
ttxc/utils.py
ttxc/errors/__init__.py
ttxc/types/__init__.py
ttxc/types/payer.py
ttxc/types/receiver.py
ttxc/types/transaction.py
telebirrTxChecker-0.0.6.dist-info/METADATA
telebirrTxChecker-0.0.6.dist-info/WHEEL
telebirrTxChecker-0.0.6.dist-info/top_level.txt
telebirrTxChecker-0.0.6.dist-info/RECORD
