Metadata-Version: 2.1
Name: telebirrTxChecker
Version: 0.0.6
Summary: asynchronous telebirr transaction checker
Home-page: https://github.com/wizkiye/TelebirrPaymentProcessor
Author: Kidus
Author-email: wizkiye@gmail.com
License: MIT
Requires-Dist: httpx
Requires-Dist: bs4
Requires-Dist: lxml
